sorix/__init__.py
sorix/clustering/__init__.py
sorix/clustering/k_means.py
sorix/cuda/__init__.py
sorix/cuda/cuda.py
sorix/cupy/cupy.py
sorix/datasets/__init__.py
sorix/datasets/dataloader.py
sorix/datasets/dataset.py
sorix/datasets/train_test.py
sorix/metrics/__init__.py
sorix/metrics/metrics.py
sorix/nn/__init__.py
sorix/nn/layers.py
sorix/nn/loss.py
sorix/nn/net.py
sorix/optim/__init__.py
sorix/optim/optim.py
sorix/preprocessing/__init__.py
sorix/preprocessing/enconders.py
sorix/preprocessing/scalers.py
sorix/preprocessing/transformers.py
sorix/tensor/tensor.py
sorix/utils/math.py
sorix/utils/utils.py
sorix-1.0.0.dist-info/licenses/LICENSE
sorix-1.0.0.dist-info/METADATA
sorix-1.0.0.dist-info/WHEEL
sorix-1.0.0.dist-info/top_level.txt
sorix-1.0.0.dist-info/RECORD
