Metadata-Version: 2.4
Name: sorix
Version: 1.0.0
Summary: A minimalistic framework for building neural networks in Python.
Author-email: Mitchell Mirano <mitchellmirano25@gmail.com>
Requires-Python: >=3.12
License-File: LICENSE
Requires-Dist: numpy>=2.0
Provides-Extra: cp13
Requires-Dist: cupy-cuda13x>=13.0; extra == "cp13"
Requires-Dist: numpy<3.0,>=2.0; extra == "cp13"
Dynamic: license-file
